meuscontrolesflet_leo/__init__.py
meuscontrolesflet_leo/meus_controles.py
meuscontrolesflet_leo-0.1.0.dist-info/METADATA
meuscontrolesflet_leo-0.1.0.dist-info/WHEEL
meuscontrolesflet_leo-0.1.0.dist-info/RECORD
