Metadata-Version: 2.1
Name: meuscontrolesflet-leo
Version: 0.1.0
Summary: 
Author: leomoraesguitar
Author-email: 123950901+leomoraesguitar@users.noreply.github.com
Requires-Python: >=3.11,<4.0
Classifier: Programming Language :: Python :: 3
Classifier: Programming Language :: Python :: 3.11
Requires-Dist: flet (>=0.18.0,<0.19.0)
